[
  {
    "ad_id": "913631961560129",
    "brand": "PUMA",
    "title": "=PUMA Tackle Heritage low-top sneakers combining retro design with modern street style.",
    "offer": "=PUMA Tackle Heritage低筒運動鞋結合復古設計與現代街頭風格。",
    "lang": "bilingual",
    "score": "=5",
    "logo": "=https://scontent-phl2-1.xx.fbcdn.net/v/t39.35426-6/649975804_1600059834551052_372746243282586308_n.jpg?stp=dst-jpg_s60x60_tt6&_nc_cat=102&ccb=1-7&_nc_sid=c53f8f&_nc_ohc=fHZGgzJVOVkQ7kNvwHnmoqg&_nc_oc=Adm4X1W6uOZoyODFvNWzUhg1yOLjRMN9W9Qkht9aRaPascscGxs95icow5FRvRWiFfg&_nc_zt=14&_nc_ht=scontent-phl2-1.xx&_nc_gid=zQ9r_HeKzETn_DwETUHBLw&_nc_ss=8&oh=00_AfzCnzA8JCmjHo5ODjtF835CR-TlbS4a8pSRuUMnLIghSQ&oe=69BEDBE0",
    "image_url": "=https://scontent-phl2-1.xx.fbcdn.net/v/t39.35426-6/649925126_1482914309913886_8288121311804194299_n.jpg?stp=dst-jpg_s600x600_tt6&_nc_cat=110&ccb=1-7&_nc_sid=c53f8f&_nc_ohc=uEKbI6C5-XEQ7kNvwHzyO4G&_nc_oc=Adl5S7Zg-qNOg8YlK9nrvDZxSPIjcLUX8EyzrqcscvLaLj7Nl4TchdGH_z8eVLGVgoE&_nc_zt=14&_nc_ht=scontent-phl2-1.xx&_nc_gid=zQ9r_HeKzETn_DwETUHBLw&_nc_ss=8&oh=00_Afxx3UBFqCtIYsnGr43ZOHTjwH2agg7W_GGkTtzvH2tOEA&oe=69BED735",
    "video_url": "=",
    "category": "fashion",
    "valid_until": "",
    "scraped_at": "2026-03-17T10:33:20.513257",
    "ad_library_url": "=https://www.facebook.com/ads/library/?id=913631961560129"
  },
  {
    "ad_id": "1231401345745657",
    "brand": "PUMA",
    "title": "=New Scuderia Ferrari HP collection launches with classic red and white colors.",
    "offer": "=全新 Scuderia Ferrari HP 系列推出，採用經典紅白配色。",
    "lang": "bilingual",
    "score": "=6",
    "logo": "=https://scontent-phl2-1.xx.fbcdn.net/v/t39.35426-6/645613623_2335660953580991_4379086740304830610_n.jpg?stp=dst-jpg_s60x60_tt6&_nc_cat=105&ccb=1-7&_nc_sid=c53f8f&_nc_ohc=gWPA49zdcPMQ7kNvwF_sjXG&_nc_oc=AdncVSgq0jHCgkm-c2NGhr0CXiEKc8NtAbS8tye0Fum7B_eSHVl3FcUCwxWAmdN-AiY&_nc_zt=14&_nc_ht=scontent-phl2-1.xx&_nc_gid=zQ9r_HeKzETn_DwETUHBLw&_nc_ss=8&oh=00_AfxfD5gM2qxp9u4lxaxC9qOLy_ab1x5iAvGRto_RkuAwVQ&oe=69BEE891",
    "image_url": "=https://scontent-phl2-1.xx.fbcdn.net/v/t39.35426-6/646839346_770231799493246_161614654972176648_n.jpg?stp=dst-jpg_s600x600_tt6&_nc_cat=105&ccb=1-7&_nc_sid=c53f8f&_nc_ohc=AxTK0hzoo2IQ7kNvwGXBtUD&_nc_oc=AdkE3sr7pAvUTbFA8ZznVLXC7fQDytPGsfMjke__EeuMGWtP-RkG7MtPD-Ab2wNwvxE&_nc_zt=14&_nc_ht=scontent-phl2-1.xx&_nc_gid=zQ9r_HeKzETn_DwETUHBLw&_nc_ss=8&oh=00_Afx8F99SY5sj10agI0baAkRBBnOg-s2x3sipss9Dn0OBkw&oe=69BEF3F3",
    "video_url": "=",
    "category": "fashion",
    "valid_until": "",
    "scraped_at": "2026-03-17T10:33:20.512675",
    "ad_library_url": "=https://www.facebook.com/ads/library/?id=1231401345745657"
  },
  {
    "ad_id": "1294515815860317",
    "brand": "PUMA",
    "title": "=PUMA launches HYROX-exclusive Deviate NITRO Elite 4 running shoe.",
    "offer": "=PUMA推出HYROX專屬Deviate NITRO Elite 4跑鞋。",
    "lang": "bilingual",
    "score": "=6",
    "logo": "=https://scontent-phl2-1.xx.fbcdn.net/v/t39.35426-6/651000469_1620196149134355_4683689554407778825_n.jpg?stp=dst-jpg_s60x60_tt6&_nc_cat=101&ccb=1-7&_nc_sid=c53f8f&_nc_ohc=cdvu7I-e17sQ7kNvwHFA6GK&_nc_oc=AdnzHERljMmWoxm7OlPpAW_qH0JCoquoX98LZ9uc5EJFmT9SXlAZjmMv6KGT2opo_0U&_nc_zt=14&_nc_ht=scontent-phl2-1.xx&_nc_gid=zQ9r_HeKzETn_DwETUHBLw&_nc_ss=8&oh=00_AfxTnQ-uMN-SpMT2Yby3KChmHWhMsr2ZKDIJejjuZ_JeBg&oe=69BEF246",
    "image_url": "=https://scontent-phl2-1.xx.fbcdn.net/v/t39.35426-6/651706430_2829018687273088_3271254040727777310_n.jpg?stp=dst-jpg_s600x600_tt6&_nc_cat=111&ccb=1-7&_nc_sid=c53f8f&_nc_ohc=uUCqlhsUT70Q7kNvwFjTTCg&_nc_oc=Adk1KgNlZ30PkzL3TgTUeZKnxaCTFGH7u0_CJdcCmSBHCYlqHVlJuGJejeqm3q_uxQI&_nc_zt=14&_nc_ht=scontent-phl2-1.xx&_nc_gid=zQ9r_HeKzETn_DwETUHBLw&_nc_ss=8&oh=00_AfxR6vT9q5ol_gbHDNSW3cm1smC3NpvhyJUG6XV1Zq1_LQ&oe=69BEF790",
    "video_url": "=",
    "category": "fashion",
    "valid_until": "",
    "scraped_at": "2026-03-17T10:33:20.511118",
    "ad_library_url": "=https://www.facebook.com/ads/library/?id=1294515815860317"
  },
  {
    "ad_id": "914165574941691",
    "brand": "PUMA",
    "title": "=PUMA McLaren racing collection with iconic orange and black colorway now available.",
    "offer": "=PUMA推出麥拿侖賽車系列，採用標誌性橙黑配色。",
    "lang": "zh",
    "score": "=6",
    "logo": "=https://scontent-phl2-1.xx.fbcdn.net/v/t39.35426-6/648423911_919797783793998_2152597225680591247_n.jpg?stp=dst-jpg_s60x60_tt6&_nc_cat=106&ccb=1-7&_nc_sid=c53f8f&_nc_ohc=29Q6uDYCvXwQ7kNvwHXp2hV&_nc_oc=Adk-WfhTF4dnOwhp3koUCgwC-i4Plx3fI-tmgu3FFM3OMCZmwOOQgsFnyRd_2GmR3Og&_nc_zt=14&_nc_ht=scontent-phl2-1.xx&_nc_gid=zQ9r_HeKzETn_DwETUHBLw&_nc_ss=8&oh=00_AfzAkYf8hMMcIY-8YenNXyxP7Ynqwdva5lG1N5wxbCp8vA&oe=69BEE4D3",
    "image_url": "=https://scontent-phl2-1.xx.fbcdn.net/v/t39.35426-6/648423911_1937430554314396_1672629084786447186_n.jpg?stp=dst-jpg_s600x600_tt6&_nc_cat=111&ccb=1-7&_nc_sid=c53f8f&_nc_ohc=xTEuEf0ZMdUQ7kNvwGNCq-Q&_nc_oc=AdmMoxXLXk7JgrN2Y9cvlJHqlHUGjbbqzk7g4NkRorfMUXxJ4qH69n1bJhWvLYkr27Q&_nc_zt=14&_nc_ht=scontent-phl2-1.xx&_nc_gid=zQ9r_HeKzETn_DwETUHBLw&_nc_ss=8&oh=00_AfyBoQ9IXkrCkeHYp-ff14QoSsMjK4x-OXx_YENyxdA_6A&oe=69BEDCB4",
    "video_url": "=",
    "category": "fashion",
    "valid_until": "",
    "scraped_at": "2026-03-17T10:33:20.510521",
    "ad_library_url": "=https://www.facebook.com/ads/library/?id=914165574941691"
  },
  {
    "ad_id": "4248517892077851",
    "brand": "PUMA",
    "title": "=New Deviate NITRO Elite 4 racing shoe with upgraded foam and carbon plate technology.",
    "offer": "=全新 Deviate NITRO™ Elite 4 跑鞋，採用升級泡棉和碳板技術。",
    "lang": "zh",
    "score": "=6",
    "logo": "=https://scontent-phl2-1.xx.fbcdn.net/v/t39.35426-6/633374165_1185682343648535_5258813578057456210_n.jpg?stp=dst-jpg_s60x60_tt6&_nc_cat=101&ccb=1-7&_nc_sid=c53f8f&_nc_ohc=pmOL3gDzwnMQ7kNvwFhiqks&_nc_oc=AdkC1piyKeqA8yNG6QwvIFd6DjY_MsTuiL2znSaXcHdLLvuIHCCjXgr4TYg9li6_4os&_nc_zt=14&_nc_ht=scontent-phl2-1.xx&_nc_gid=zQ9r_HeKzETn_DwETUHBLw&_nc_ss=8&oh=00_Afz83teNs0auCTzEviskd2CxtqI_aDLggGHZhTv6lhxShA&oe=69BEC463",
    "image_url": "=",
    "video_url": "=https://video-phl2-1.xx.fbcdn.net/o1/v/t2/f2/m366/AQN1fpS5QHDo0luCgDt8m1bUXpzVgo_Q3wrgBiO04H0lrVSkvWQEEVRViokVy8pFllLLhQpZuQh3cO0S2LSOZBSyZGJEdL55GNnLQW__Yd4RDA.mp4?_nc_cat=106&_nc_sid=5e9851&_nc_ht=video-phl2-1.xx.fbcdn.net&_nc_ohc=VRMeW9-DL4YQ7kNvwGsvgyz&efg=eyJ2ZW5jb2RlX3RhZyI6Inhwdl9wcm9ncmVzc2l2ZS5WSV9VU0VDQVNFX1BST0RVQ1RfVFlQRS4uQzMuNzIwLmRhc2hfaDI2NC1iYXNpYy1nZW4yXzcyMHAiLCJ4cHZfYXNzZXRfaWQiOjE3NTg0ODI3MDg0NDM1ODcsImFzc2V0X2FnZV9kYXlzIjozNCwidmlfdXNlY2FzZV9pZCI6MTA3OTksImR1cmF0aW9uX3MiOjE1LCJ1cmxnZW5fc291cmNlIjoid3d3In0%3D&ccb=17-1&vs=f62c6fcdf0e6ba29&_nc_vs=HBksFQIYRWZiX2VwaGVtZXJhbC84MzRDNjQ1NDgxODYxODE1MjY0MzU5MDk4MUIyMERCQ19tdF8xX3ZpZGVvX2Rhc2hpbml0Lm1wNBUAAsgBEgAVAhhAZmJfcGVybWFuZW50LzVFNDYwQjE1NDE4MzgwODZEQUI2QkVDMTRFNEE1RkJDX2F1ZGlvX2Rhc2hpbml0Lm1wNBUCAsgBEgAoABgAGwKIB3VzZV9vaWwBMRJwcm9ncmVzc2l2ZV9yZWNpcGUBMRUAACaGx_GSldWfBhUCKAJDMywXQC4HrhR64UgYGWRhc2hfaDI2NC1iYXNpYy1nZW4yXzcyMHARAHUAZd6oAQA&_nc_gid=zQ9r_HeKzETn_DwETUHBLw&_nc_ss=8&_nc_zt=28&oh=00_AfygWvMQqmRkqPuova9JMxJKcx_zJm_n85II84jSWvufzg&oe=69BEF5DA",
    "category": "fashion",
    "valid_until": "",
    "scraped_at": "2026-03-17T10:33:20.509294",
    "ad_library_url": "=https://www.facebook.com/ads/library/?id=4248517892077851"
  },
  {
    "ad_id": "2428822134247207",
    "brand": "PUMA",
    "title": "=New Scuderia Ferrari HP collection launches with classic red-white colorway honoring Ferrari heritage.",
    "offer": "=全新Scuderia Ferrari HP系列登場，以經典紅白配色致敬法拉利傳奇血統。",
    "lang": "bilingual",
    "score": "=6",
    "logo": "=https://scontent-phl2-1.xx.fbcdn.net/v/t39.35426-6/649283135_860825833675084_5060663408680296361_n.jpg?stp=dst-jpg_s60x60_tt6&_nc_cat=102&ccb=1-7&_nc_sid=c53f8f&_nc_ohc=kRhA7Z762aQQ7kNvwFOvVNq&_nc_oc=AdkkrCv3VM1iSdWNn_cHyHgkIh8Mf70gujtgqBY_CxQE4WxQn6pwV1d1dx7P9gv5gcE&_nc_zt=14&_nc_ht=scontent-phl2-1.xx&_nc_gid=zQ9r_HeKzETn_DwETUHBLw&_nc_ss=8&oh=00_AfwAhpH7AugS8Rt0h1rWxmZsXlmESL3HCeWIYbRgFG_0PQ&oe=69BEE0F3",
    "image_url": "=https://scontent-phl2-1.xx.fbcdn.net/v/t39.35426-6/648521508_807142388426159_1820666738246726136_n.jpg?stp=dst-jpg_s600x600_tt6&_nc_cat=107&ccb=1-7&_nc_sid=c53f8f&_nc_ohc=w8loMWa875EQ7kNvwGOr60V&_nc_oc=Adm3P6z8oDIL5Uww1HgDILfRn-FjH_ur1_yoDAWHyw2qKfnKtqMDoadd8OVFusBm_2s&_nc_zt=14&_nc_ht=scontent-phl2-1.xx&_nc_gid=zQ9r_HeKzETn_DwETUHBLw&_nc_ss=8&oh=00_Afy18qJmoBxMSm5dgoyPhiamlCEKmmtMrMisnQ6xLLjgQw&oe=69BED912",
    "video_url": "=",
    "category": "fashion",
    "valid_until": "",
    "scraped_at": "2026-03-17T10:33:20.508366",
    "ad_library_url": "=https://www.facebook.com/ads/library/?id=2428822134247207"
  },
  {
    "ad_id": "1665664431442815",
    "brand": "PUMA",
    "title": "=ROSÉ reimagines classic H-Street sneaker with modern aesthetic.",
    "offer": "=ROSÉ 重新詮釋 H-Street 經典鞋款，注入現代美學。",
    "lang": "zh",
    "score": "=6",
    "logo": "=https://scontent-phl2-1.xx.fbcdn.net/v/t39.35426-6/649492359_2060621671460932_7863886657529141095_n.jpg?stp=dst-jpg_s60x60_tt6&_nc_cat=103&ccb=1-7&_nc_sid=c53f8f&_nc_ohc=ctU3mQBsjc4Q7kNvwECMhax&_nc_oc=AdkKq5THizPIGvsFbJSc0Nqk5f88RywS-VAYAAV_Sjh0PBotJw5N3dpCo3bp7_pAOK0&_nc_zt=14&_nc_ht=scontent-phl2-1.xx&_nc_gid=zQ9r_HeKzETn_DwETUHBLw&_nc_ss=8&oh=00_Afw_7buEOmue2Pzuolh3W6xJ40k8GZmdilb5uXJI6JjeSw&oe=69BEE490",
    "image_url": "=",
    "video_url": "=https://video-phl2-1.xx.fbcdn.net/o1/v/t2/f2/m366/AQNsguAuIEnTyVYedYJvVojcy8Yq-xrPEcT9q8HbW7RUcHrJQdRTueg7aXbS_f9Opc4AHHPkuzKDFL0ISaPSYjezYE7mAGJjqxVi6lhC6jEasA.mp4?_nc_cat=110&_nc_sid=5e9851&_nc_ht=video-phl2-1.xx.fbcdn.net&_nc_ohc=3iDepl3jG5kQ7kNvwGdeIJ6&efg=eyJ2ZW5jb2RlX3RhZyI6Inhwdl9wcm9ncmVzc2l2ZS5WSV9VU0VDQVNFX1BST0RVQ1RfVFlQRS4uQzMuNzIwLmRhc2hfaDI2NC1iYXNpYy1nZW4yXzcyMHAiLCJ4cHZfYXNzZXRfaWQiOjIwMzE3OTM2MTA3MDk5NjgsImFzc2V0X2FnZV9kYXlzIjo1LCJ2aV91c2VjYXNlX2lkIjoxMDc5OSwiZHVyYXRpb25fcyI6MTUsInVybGdlbl9zb3VyY2UiOiJ3d3cifQ%3D%3D&ccb=17-1&vs=edf5c78b0fab6b1d&_nc_vs=HBksFQIYRWZiX2VwaGVtZXJhbC84MjQwQzZBRTc4MjA0OTNEQjRCMzk1QjAyOEYwOURCRF9tdF8xX3ZpZGVvX2Rhc2hpbml0Lm1wNBUAAsgBEgAVAhhAZmJfcGVybWFuZW50LzI4NDk2NDEwNTc5OEM2Mzc5QjQ1Qzc5NTA0MUM5MDlGX2F1ZGlvX2Rhc2hpbml0Lm1wNBUCAsgBEgAoABgAGwKIB3VzZV9vaWwBMRJwcm9ncmVzc2l2ZV9yZWNpcGUBMRUAACag7-KG-vmbBxUCKAJDMywXQC4AAAAAAAAYGWRhc2hfaDI2NC1iYXNpYy1nZW4yXzcyMHARAHUAZd6oAQA&_nc_gid=zQ9r_HeKzETn_DwETUHBLw&_nc_ss=8&_nc_zt=28&oh=00_AfwX3rcg_-fFDggu2UkBHPCgwm6qcybVC6oDZcy_HchSoA&oe=69BECCA2",
    "category": "fashion",
    "valid_until": "",
    "scraped_at": "2026-03-17T10:33:20.506971",
    "ad_library_url": "=https://www.facebook.com/ads/library/?id=1665664431442815"
  },
  {
    "ad_id": "782535428231893",
    "brand": "PUMA",
    "title": "=New Deviate NITRO Elite 4 racing shoe with upgraded NITROFOAM and PWRPLATE technology.",
    "offer": "=全新 Deviate NITRO™ Elite 4 專業比賽跑鞋，採用升級 NITROFOAM 及 PWRPLATE 碳板。",
    "lang": "zh",
    "score": "=6",
    "logo": "=https://scontent-phl2-1.xx.fbcdn.net/v/t39.35426-6/627914992_1284939173524085_2922394981737064873_n.jpg?stp=dst-jpg_s60x60_tt6&_nc_cat=100&ccb=1-7&_nc_sid=c53f8f&_nc_ohc=J3L0BV1AT8QQ7kNvwGnrJCG&_nc_oc=AdnB2pBZ9yF1JEOcPeWEbY5X_wYWS5K1TyAPUGGbcAn2Kl2iIZg5jscfQE9kc1MXV7o&_nc_zt=14&_nc_ht=scontent-phl2-1.xx&_nc_gid=zQ9r_HeKzETn_DwETUHBLw&_nc_ss=8&oh=00_AfxYueGTdbvozrO5xQZiz23F5kZvazz8zjYQiwy1UxXksA&oe=69BEDB53",
    "image_url": "=",
    "video_url": "=https://video-phl2-1.xx.fbcdn.net/o1/v/t2/f2/m366/AQN1fpS5QHDo0luCgDt8m1bUXpzVgo_Q3wrgBiO04H0lrVSkvWQEEVRViokVy8pFllLLhQpZuQh3cO0S2LSOZBSyZGJEdL55GNnLQW__Yd4RDA.mp4?_nc_cat=106&_nc_sid=5e9851&_nc_ht=video-phl2-1.xx.fbcdn.net&_nc_ohc=VRMeW9-DL4YQ7kNvwGsvgyz&efg=eyJ2ZW5jb2RlX3RhZyI6Inhwdl9wcm9ncmVzc2l2ZS5WSV9VU0VDQVNFX1BST0RVQ1RfVFlQRS4uQzMuNzIwLmRhc2hfaDI2NC1iYXNpYy1nZW4yXzcyMHAiLCJ4cHZfYXNzZXRfaWQiOjE3NTg0ODI3MDg0NDM1ODcsImFzc2V0X2FnZV9kYXlzIjozNCwidmlfdXNlY2FzZV9pZCI6MTA3OTksImR1cmF0aW9uX3MiOjE1LCJ1cmxnZW5fc291cmNlIjoid3d3In0%3D&ccb=17-1&vs=f62c6fcdf0e6ba29&_nc_vs=HBksFQIYRWZiX2VwaGVtZXJhbC84MzRDNjQ1NDgxODYxODE1MjY0MzU5MDk4MUIyMERCQ19tdF8xX3ZpZGVvX2Rhc2hpbml0Lm1wNBUAAsgBEgAVAhhAZmJfcGVybWFuZW50LzVFNDYwQjE1NDE4MzgwODZEQUI2QkVDMTRFNEE1RkJDX2F1ZGlvX2Rhc2hpbml0Lm1wNBUCAsgBEgAoABgAGwKIB3VzZV9vaWwBMRJwcm9ncmVzc2l2ZV9yZWNpcGUBMRUAACaGx_GSldWfBhUCKAJDMywXQC4HrhR64UgYGWRhc2hfaDI2NC1iYXNpYy1nZW4yXzcyMHARAHUAZd6oAQA&_nc_gid=zQ9r_HeKzETn_DwETUHBLw&_nc_ss=8&_nc_zt=28&oh=00_AfygWvMQqmRkqPuova9JMxJKcx_zJm_n85II84jSWvufzg&oe=69BEF5DA",
    "category": "fashion",
    "valid_until": "",
    "scraped_at": "2026-03-17T10:33:20.506319",
    "ad_library_url": "=https://www.facebook.com/ads/library/?id=782535428231893"
  },
  {
    "ad_id": "936846468924184",
    "brand": "PUMA",
    "title": "=ROSÉ reimagines classic H-Street sneakers with modern millennial vibes.",
    "offer": "=ROSÉ 以清冷魅力重新詮釋經典 H-Street 鞋款，注入現代千禧氣息。",
    "lang": "zh",
    "score": "=6",
    "logo": "=https://scontent-phl2-1.xx.fbcdn.net/v/t39.35426-6/649391852_864014436662804_6776972748641450593_n.jpg?stp=dst-jpg_s60x60_tt6&_nc_cat=108&ccb=1-7&_nc_sid=c53f8f&_nc_ohc=ubBt8GRK9K8Q7kNvwG3zpuS&_nc_oc=AdllaGGELma6-UQU0BpbLz7NIXLUNolH1AtiTSyrQxOHt7gPAzL5573-URgxfALHxYQ&_nc_zt=14&_nc_ht=scontent-phl2-1.xx&_nc_gid=zQ9r_HeKzETn_DwETUHBLw&_nc_ss=8&oh=00_AfzUHWvCyiJVfywP-2mkjo0ApGDRr2eCe3ZrTvBRMok0gw&oe=69BEF17E",
    "image_url": "=",
    "video_url": "=https://video-phl2-1.xx.fbcdn.net/o1/v/t2/f2/m366/AQNsguAuIEnTyVYedYJvVojcy8Yq-xrPEcT9q8HbW7RUcHrJQdRTueg7aXbS_f9Opc4AHHPkuzKDFL0ISaPSYjezYE7mAGJjqxVi6lhC6jEasA.mp4?_nc_cat=110&_nc_sid=5e9851&_nc_ht=video-phl2-1.xx.fbcdn.net&_nc_ohc=3iDepl3jG5kQ7kNvwGdeIJ6&efg=eyJ2ZW5jb2RlX3RhZyI6Inhwdl9wcm9ncmVzc2l2ZS5WSV9VU0VDQVNFX1BST0RVQ1RfVFlQRS4uQzMuNzIwLmRhc2hfaDI2NC1iYXNpYy1nZW4yXzcyMHAiLCJ4cHZfYXNzZXRfaWQiOjIwMzE3OTM2MTA3MDk5NjgsImFzc2V0X2FnZV9kYXlzIjo1LCJ2aV91c2VjYXNlX2lkIjoxMDc5OSwiZHVyYXRpb25fcyI6MTUsInVybGdlbl9zb3VyY2UiOiJ3d3cifQ%3D%3D&ccb=17-1&vs=edf5c78b0fab6b1d&_nc_vs=HBksFQIYRWZiX2VwaGVtZXJhbC84MjQwQzZBRTc4MjA0OTNEQjRCMzk1QjAyOEYwOURCRF9tdF8xX3ZpZGVvX2Rhc2hpbml0Lm1wNBUAAsgBEgAVAhhAZmJfcGVybWFuZW50LzI4NDk2NDEwNTc5OEM2Mzc5QjQ1Qzc5NTA0MUM5MDlGX2F1ZGlvX2Rhc2hpbml0Lm1wNBUCAsgBEgAoABgAGwKIB3VzZV9vaWwBMRJwcm9ncmVzc2l2ZV9yZWNpcGUBMRUAACag7-KG-vmbBxUCKAJDMywXQC4AAAAAAAAYGWRhc2hfaDI2NC1iYXNpYy1nZW4yXzcyMHARAHUAZd6oAQA&_nc_gid=zQ9r_HeKzETn_DwETUHBLw&_nc_ss=8&_nc_zt=28&oh=00_AfwX3rcg_-fFDggu2UkBHPCgwm6qcybVC6oDZcy_HchSoA&oe=69BECCA2",
    "category": "fashion",
    "valid_until": "",
    "scraped_at": "2026-03-17T10:33:20.504377",
    "ad_library_url": "=https://www.facebook.com/ads/library/?id=936846468924184"
  },
  {
    "ad_id": "1238044528304501",
    "brand": "PUMA",
    "title": "=New Scuderia Ferrari HP collection launches with classic red and white design.",
    "offer": "=全新 Scuderia Ferrari HP 系列正式推出，以經典紅白配色呈現。",
    "lang": "bilingual",
    "score": "=6",
    "logo": "=https://scontent-phl2-1.xx.fbcdn.net/v/t39.35426-6/646195275_1240415764289820_9203622270535804329_n.jpg?stp=dst-jpg_s60x60_tt6&_nc_cat=108&ccb=1-7&_nc_sid=c53f8f&_nc_ohc=d6xtFyjl67EQ7kNvwHPFlzc&_nc_oc=AdmIDx8wTcXOpKuNVNo8gHPs3sFFX_CJZznV4eGkHT7qVjwfiKT4wxbZkczRU9z4jV0&_nc_zt=14&_nc_ht=scontent-phl2-1.xx&_nc_gid=zQ9r_HeKzETn_DwETUHBLw&_nc_ss=8&oh=00_Afwg-2D_WKusOmNmckuf3-iQBqtvRtZAMWAa_5Vvap2IYw&oe=69BEF572",
    "image_url": "=https://scontent-phl2-1.xx.fbcdn.net/v/t39.35426-6/646388917_1898073464149627_2562694054082414140_n.jpg?stp=dst-jpg_s600x600_tt6&_nc_cat=110&ccb=1-7&_nc_sid=c53f8f&_nc_ohc=R4SkM8jSmMYQ7kNvwHg5Yj2&_nc_oc=AdlE5c7Uh_1Dqr8gihmyF2AFT1sfz4aV7FBxhtPJqngC5vXeET4e3JXobF9hRKFvRkY&_nc_zt=14&_nc_ht=scontent-phl2-1.xx&_nc_gid=zQ9r_HeKzETn_DwETUHBLw&_nc_ss=8&oh=00_AfzMCJ7cHb4aOKmGnKkxBshmTGa2xRqio18sM_prhAmJow&oe=69BEDABF",
    "video_url": "=",
    "category": "fashion",
    "valid_until": "",
    "scraped_at": "2026-03-17T10:33:20.503801",
    "ad_library_url": "=https://www.facebook.com/ads/library/?id=1238044528304501"
  },
  {
    "ad_id": "4557944847827603",
    "brand": "PUMA",
    "title": "=New Deviate NITRO Elite 4 running shoe with upgraded performance technology.",
    "offer": "=全新 Deviate NITRO™ Elite 4 跑鞋，採用升級性能科技。",
    "lang": "zh",
    "score": "=6",
    "logo": "=https://scontent-phl2-1.xx.fbcdn.net/v/t39.35426-6/631509148_924846976730608_2387582201022586617_n.jpg?stp=dst-jpg_s60x60_tt6&_nc_cat=100&ccb=1-7&_nc_sid=c53f8f&_nc_ohc=bRarjJ6N3nYQ7kNvwGwSK9A&_nc_oc=AdnJqExh534EnskCRCQYnKXb_lLDwE2vCBRLIoYqbMT_HS3FHfow6VZ24khlm2Y7uzQ&_nc_zt=14&_nc_ht=scontent-phl2-1.xx&_nc_gid=zQ9r_HeKzETn_DwETUHBLw&_nc_ss=8&oh=00_AfxHFC7yb43wt4M2NRJfK59q3xOYmor6v512QPs1TN2cBQ&oe=69BEE6F1",
    "image_url": "=",
    "video_url": "=https://video-phl2-1.xx.fbcdn.net/o1/v/t2/f2/m366/AQN1fpS5QHDo0luCgDt8m1bUXpzVgo_Q3wrgBiO04H0lrVSkvWQEEVRViokVy8pFllLLhQpZuQh3cO0S2LSOZBSyZGJEdL55GNnLQW__Yd4RDA.mp4?_nc_cat=106&_nc_sid=5e9851&_nc_ht=video-phl2-1.xx.fbcdn.net&_nc_ohc=VRMeW9-DL4YQ7kNvwGsvgyz&efg=eyJ2ZW5jb2RlX3RhZyI6Inhwdl9wcm9ncmVzc2l2ZS5WSV9VU0VDQVNFX1BST0RVQ1RfVFlQRS4uQzMuNzIwLmRhc2hfaDI2NC1iYXNpYy1nZW4yXzcyMHAiLCJ4cHZfYXNzZXRfaWQiOjE3NTg0ODI3MDg0NDM1ODcsImFzc2V0X2FnZV9kYXlzIjozNCwidmlfdXNlY2FzZV9pZCI6MTA3OTksImR1cmF0aW9uX3MiOjE1LCJ1cmxnZW5fc291cmNlIjoid3d3In0%3D&ccb=17-1&vs=f62c6fcdf0e6ba29&_nc_vs=HBksFQIYRWZiX2VwaGVtZXJhbC84MzRDNjQ1NDgxODYxODE1MjY0MzU5MDk4MUIyMERCQ19tdF8xX3ZpZGVvX2Rhc2hpbml0Lm1wNBUAAsgBEgAVAhhAZmJfcGVybWFuZW50LzVFNDYwQjE1NDE4MzgwODZEQUI2QkVDMTRFNEE1RkJDX2F1ZGlvX2Rhc2hpbml0Lm1wNBUCAsgBEgAoABgAGwKIB3VzZV9vaWwBMRJwcm9ncmVzc2l2ZV9yZWNpcGUBMRUAACaGx_GSldWfBhUCKAJDMywXQC4HrhR64UgYGWRhc2hfaDI2NC1iYXNpYy1nZW4yXzcyMHARAHUAZd6oAQA&_nc_gid=zQ9r_HeKzETn_DwETUHBLw&_nc_ss=8&_nc_zt=28&oh=00_AfygWvMQqmRkqPuova9JMxJKcx_zJm_n85II84jSWvufzg&oe=69BEF5DA",
    "category": "fashion",
    "valid_until": "",
    "scraped_at": "2026-03-17T10:33:20.502700",
    "ad_library_url": "=https://www.facebook.com/ads/library/?id=4557944847827603"
  },
  {
    "ad_id": "1237012021917835",
    "brand": "PUMA",
    "title": "=McLaren racing collection featuring iconic orange and black colorway now available.",
    "offer": "=麥拿侖賽車系列採用標誌性橙黑配色現已推出。",
    "lang": "zh",
    "score": "=6",
    "logo": "=https://scontent-phl2-1.xx.fbcdn.net/v/t39.35426-6/645493830_26461915566759574_8187479806031159735_n.jpg?stp=dst-jpg_s60x60_tt6&_nc_cat=102&ccb=1-7&_nc_sid=c53f8f&_nc_ohc=-kCGCAJ2VrUQ7kNvwE_GLYi&_nc_oc=AdkUoypp9fCfNO4q2Y9EPOROFTy7xdFADaH5MaR5xtFB8ySQVypYYlLJd-Is2DBO0Go&_nc_zt=14&_nc_ht=scontent-phl2-1.xx&_nc_gid=zQ9r_HeKzETn_DwETUHBLw&_nc_ss=8&oh=00_AfwgChwtEz3crjqXLUNUxS-iZz3ojKAEeEv90UlpF-L1KQ&oe=69BEC8C0",
    "image_url": "=https://scontent-phl2-1.xx.fbcdn.net/v/t39.35426-6/647535706_943403941708681_5305868523705948196_n.jpg?stp=dst-jpg_s600x600_tt6&_nc_cat=108&ccb=1-7&_nc_sid=c53f8f&_nc_ohc=qDt759YaSTUQ7kNvwFkENTw&_nc_oc=AdnT-MmjfijAdaipBGAVV_BTq8xK3jEWHr9h6n6j12uWGEmHHOUKFe8qn4_uJcYMv8Y&_nc_zt=14&_nc_ht=scontent-phl2-1.xx&_nc_gid=zQ9r_HeKzETn_DwETUHBLw&_nc_ss=8&oh=00_Afx239CE0eyjA-RX59pNcIWYZ7a123qCUSswFzG5jQHnEA&oe=69BED678",
    "video_url": "=",
    "category": "fashion",
    "valid_until": "",
    "scraped_at": "2026-03-17T10:33:20.500850",
    "ad_library_url": "=https://www.facebook.com/ads/library/?id=1237012021917835"
  },
  {
    "ad_id": "1926092167996602",
    "brand": "PUMA",
    "title": "=PUMA offers new seasonal sports and fashion products with free shipping and exclusive member benefits.",
    "offer": "=PUMA推出全新季度運動及時尚產品，免運費及會員專屬優惠。",
    "lang": "zh",
    "score": "=6",
    "logo": "=https://scontent-fco2-1.xx.fbcdn.net/v/t39.35426-6/586607159_1513927239842868_3255649684187022733_n.jpg?stp=dst-jpg_s60x60_tt6&_nc_cat=109&ccb=1-7&_nc_sid=c53f8f&_nc_ohc=TArj_BXWk9MQ7kNvwEyBzeQ&_nc_oc=AdmIGqX7qq88j2mFqS4SXRurMOl00MMskeMGc7wBH-cO38PpOEjmEJxngFi337jn9kM&_nc_zt=14&_nc_ht=scontent-fco2-1.xx&_nc_gid=OZ3G3lHuRwmK7U8NyCsoHg&_nc_ss=8&oh=00_Afzpm94KhBm3v8HKVmN2CRj7bQnWhaxmX3gH5fh7wn6LMg&oe=69BEEE57",
    "image_url": "=https://scontent-fco2-1.xx.fbcdn.net/v/t39.35426-6/587308648_4007289596082421_1149376194354310524_n.jpg?stp=dst-jpg_s600x600_tt6&_nc_cat=108&ccb=1-7&_nc_sid=c53f8f&_nc_ohc=L48ubzv_4OEQ7kNvwFE4mIH&_nc_oc=AdkKulKJxcL1DO4zmQQJDFhZ6InP64WX8gs-DRSs4iJc-IVsTkoe9J-tLzdo1ssL0uQ&_nc_zt=14&_nc_ht=scontent-fco2-1.xx&_nc_gid=OZ3G3lHuRwmK7U8NyCsoHg&_nc_ss=8&oh=00_Afy6kpSYLdXs0i7iPd9D0Kh6JYS9TUSXXLMMc4DSgWDXmw&oe=69BEF785",
    "video_url": "=",
    "category": "fashion",
    "valid_until": "",
    "scraped_at": "2026-03-17T10:33:20.500049",
    "ad_library_url": "=https://www.facebook.com/ads/library/?id=1926092167996602"
  },
  {
    "ad_id": "1539581627109346",
    "brand": "PUMA",
    "title": "=PUMA Tackle Heritage low-top sneaker with retro design and modern street style.",
    "offer": "=PUMA Tackle Heritage 復古低筒運動鞋結合經典與現代街頭風格。",
    "lang": "bilingual",
    "score": "=5",
    "logo": "=https://scontent-fco2-1.xx.fbcdn.net/v/t39.35426-6/647554444_2445034455938910_1168853932335124987_n.jpg?stp=dst-jpg_s60x60_tt6&_nc_cat=108&ccb=1-7&_nc_sid=c53f8f&_nc_ohc=-SXKYdvJuIoQ7kNvwGyoiit&_nc_oc=AdlDrW1s-qHNCQiw3wvot3L6Imossg38t6p2a3m7vnOdleiVcc3CoK303TrsoKbwoQo&_nc_zt=14&_nc_ht=scontent-fco2-1.xx&_nc_gid=OZ3G3lHuRwmK7U8NyCsoHg&_nc_ss=8&oh=00_AfxV4kJbn8rzyoJKZACOZbyY0LiaH0sSv7behV6LTOIGRA&oe=69BEDCE3",
    "image_url": "=https://scontent-fco2-1.xx.fbcdn.net/v/t39.35426-6/646871323_861816723535413_6258411844956437560_n.jpg?stp=dst-jpg_s600x600_tt6&_nc_cat=100&ccb=1-7&_nc_sid=c53f8f&_nc_ohc=l8GriFtnZ6AQ7kNvwHeXxVB&_nc_oc=AdmYeT11qkW66OHNgiM1Y5DsDT8dMUBERHX-hztfpMVUTrBSUG7Ci8orTqjvJ1OjAjQ&_nc_zt=14&_nc_ht=scontent-fco2-1.xx&_nc_gid=OZ3G3lHuRwmK7U8NyCsoHg&_nc_ss=8&oh=00_Afy4qb6Ax4alXTaJbuoBVO2z6VrcGg6VvmUS8jeY2iqpNg&oe=69BEED73",
    "video_url": "=",
    "category": "fashion",
    "valid_until": "",
    "scraped_at": "2026-03-17T10:33:20.498638",
    "ad_library_url": "=https://www.facebook.com/ads/library/?id=1539581627109346"
  },
  {
    "ad_id": "921597240629566",
    "brand": "PUMA",
    "title": "=PUMA offers new seasonal sportswear and fashion products with free shipping and exclusive member benefits.",
    "offer": "=PUMA推出全新季度運動及時尚產品，免運費並享會員專屬優惠。",
    "lang": "zh",
    "score": "=6",
    "logo": "=https://scontent-fco2-1.xx.fbcdn.net/v/t39.35426-6/584811747_1347429716832494_6277646329634950720_n.jpg?stp=dst-jpg_s60x60_tt6&_nc_cat=100&ccb=1-7&_nc_sid=c53f8f&_nc_ohc=MeJ12FR3GzEQ7kNvwFDDbON&_nc_oc=AdnPIKJVLxb94K9UaLdxf03g12z2XAsS4nJSMeEL2rUtguyyppull0EXlQT3l1M_cNk&_nc_zt=14&_nc_ht=scontent-fco2-1.xx&_nc_gid=OZ3G3lHuRwmK7U8NyCsoHg&_nc_ss=8&oh=00_AfwhZq03EIcHIou9E5gJaM_HaKqM_agcJK1wDfp_02nMsw&oe=69BEE03A",
    "image_url": "=https://scontent-fco2-1.xx.fbcdn.net/v/t39.35426-6/584934496_854099070637056_7950346291063073082_n.jpg?stp=dst-jpg_s600x600_tt6&_nc_cat=103&ccb=1-7&_nc_sid=c53f8f&_nc_ohc=GdxHVgL3Z-AQ7kNvwE2ROV4&_nc_oc=AdlQYf7pxur7fLdtCTo1NkX0N80Nm6_HcMbo2si92cuCL_X1UoWIFwnbOpwKUHG_PF4&_nc_zt=14&_nc_ht=scontent-fco2-1.xx&_nc_gid=OZ3G3lHuRwmK7U8NyCsoHg&_nc_ss=8&oh=00_Afx8cnAp9ro2fF9aSX2EcKS3t6HE-EOcGRpsjREKKaG67Q&oe=69BEF937",
    "video_url": "=",
    "category": "fashion",
    "valid_until": "",
    "scraped_at": "2026-03-17T10:33:20.497525",
    "ad_library_url": "=https://www.facebook.com/ads/library/?id=921597240629566"
  },
  {
    "ad_id": "759347450326630",
    "brand": "PUMA",
    "title": "=PUMA Tackle Heritage low-top sneaker combining retro style with modern street attitude.",
    "offer": "=PUMA Tackle Heritage 低筒運動鞋融合復古風格與現代街頭風格。",
    "lang": "bilingual",
    "score": "=5",
    "logo": "=https://scontent-fco2-1.xx.fbcdn.net/v/t39.35426-6/646568248_798785299325230_794559251892124734_n.jpg?stp=dst-jpg_s60x60_tt6&_nc_cat=104&ccb=1-7&_nc_sid=c53f8f&_nc_ohc=CtrjiRbqaWYQ7kNvwEgcY9-&_nc_oc=AdlqPmKOJeXXTW60OvvSXHmUntsYst8O5Kl2sOTXqyshjjXgAgbUX6bIYcYLLt0OVI4&_nc_zt=14&_nc_ht=scontent-fco2-1.xx&_nc_gid=OZ3G3lHuRwmK7U8NyCsoHg&_nc_ss=8&oh=00_Afz3srik9npC5w6JzjzIf5kneGVvCD3Y1-WpmoPnS3UyUg&oe=69BEF2AC",
    "image_url": "=https://scontent-fco2-1.xx.fbcdn.net/v/t39.35426-6/647007463_913890851383854_6379105867855772204_n.jpg?stp=dst-jpg_s600x600_tt6&_nc_cat=110&ccb=1-7&_nc_sid=c53f8f&_nc_ohc=BX3EiuhcvGMQ7kNvwEKKAq7&_nc_oc=AdkYV68DldferkShKN5XhqBW6X2j99kOT_O2UYDc0xwxZ2vYostaHYjNgtMmgdgURdw&_nc_zt=14&_nc_ht=scontent-fco2-1.xx&_nc_gid=OZ3G3lHuRwmK7U8NyCsoHg&_nc_ss=8&oh=00_AfyfgO_M-4R3SO2yhKS0FNBHoSZmZtlcog1Pnq0l3z9ryg&oe=69BED602",
    "video_url": "=",
    "category": "fashion",
    "valid_until": "",
    "scraped_at": "2026-03-17T10:33:20.496608",
    "ad_library_url": "=https://www.facebook.com/ads/library/?id=759347450326630"
  },
  {
    "ad_id": "2689303084780737",
    "brand": "PUMA",
    "title": "=McLaren racing collection with iconic orange and black colorway now available.",
    "offer": "=麥拿侖賽車系列採用標誌性橙黑配色現已推出。",
    "lang": "zh",
    "score": "=6",
    "logo": "=https://scontent-fco2-1.xx.fbcdn.net/v/t39.35426-6/647155958_1442656954022292_3694671199482714495_n.jpg?stp=dst-jpg_s60x60_tt6&_nc_cat=108&ccb=1-7&_nc_sid=c53f8f&_nc_ohc=RaLXg_yMhd8Q7kNvwEGwh26&_nc_oc=AdmTYIle3dmIXoWq7QZkTurgCnxEpkDhk-Tt842tysZqSLaPOot8ttQTbiRrqqQikXE&_nc_zt=14&_nc_ht=scontent-fco2-1.xx&_nc_gid=OZ3G3lHuRwmK7U8NyCsoHg&_nc_ss=8&oh=00_AfzSB_jZZyK5vqQikxoLTyLacVZPqiMcoxhD2ZCVEci7RQ&oe=69BEEF7F",
    "image_url": "=https://scontent-fco2-1.xx.fbcdn.net/v/t39.35426-6/646547499_900181299577643_6773607264936635715_n.jpg?stp=dst-jpg_s600x600_tt6&_nc_cat=103&ccb=1-7&_nc_sid=c53f8f&_nc_ohc=wephOYUMJXYQ7kNvwFI4QHJ&_nc_oc=AdlG2w7LfDXfnsASayvRPeVJC3qAnNW_I95Q7SM9CMBcX7fnwrro64ZUH1Zlwj-y6A0&_nc_zt=14&_nc_ht=scontent-fco2-1.xx&_nc_gid=OZ3G3lHuRwmK7U8NyCsoHg&_nc_ss=8&oh=00_AfzDuo-Dnbw20jEI17hsXUNLO86lRwPBCBcXl4A-xw8ITA&oe=69BECA36",
    "video_url": "=",
    "category": "fashion",
    "valid_until": "",
    "scraped_at": "2026-03-17T10:33:20.496580",
    "ad_library_url": "=https://www.facebook.com/ads/library/?id=2689303084780737"
  },
  {
    "ad_id": "1584027789529393",
    "brand": "PUMA",
    "title": "=PUMA launches Deviate NITRO Elite 4 shoe designed exclusively for HYROX.",
    "offer": "=PUMA推出專為HYROX設計的Deviate NITRO Elite 4跑鞋。",
    "lang": "bilingual",
    "score": "=6",
    "logo": "=https://scontent-fco2-1.xx.fbcdn.net/v/t39.35426-6/651407250_904249152377916_1223478161184877440_n.jpg?stp=dst-jpg_s60x60_tt6&_nc_cat=105&ccb=1-7&_nc_sid=c53f8f&_nc_ohc=ElD8ZwvzJ2AQ7kNvwE7N05X&_nc_oc=AdnAjQ7VbQNnP8N6B8yf4c7cIXtMfBF842VLyffBMdpe4LR2qDzXtzKM35c3dHFHTn8&_nc_zt=14&_nc_ht=scontent-fco2-1.xx&_nc_gid=OZ3G3lHuRwmK7U8NyCsoHg&_nc_ss=8&oh=00_AfykGLalS9ybQCTQ_CqKDuMs6xreJFGb7mRVGOQHgAx2tw&oe=69BEFA3D",
    "image_url": "=https://scontent-fco2-1.xx.fbcdn.net/v/t39.35426-6/651079992_2743216092709610_8821425449703412080_n.jpg?stp=dst-jpg_s600x600_tt6&_nc_cat=103&ccb=1-7&_nc_sid=c53f8f&_nc_ohc=5XOSUXkK8r4Q7kNvwG6Z2KY&_nc_oc=AdlIlAac-3gJjBsfktT92xi1X2EyJ6LwfD7NoWXRlX3wFZQluMI4hdtZ4qhHXpVdTKo&_nc_zt=14&_nc_ht=scontent-fco2-1.xx&_nc_gid=OZ3G3lHuRwmK7U8NyCsoHg&_nc_ss=8&oh=00_AfyKLZLTkKOG6UoaPGk5E1eKE81UBCpHWkkvoFd8SEHelQ&oe=69BED0E8",
    "video_url": "=",
    "category": "fashion",
    "valid_until": "",
    "scraped_at": "2026-03-17T10:33:20.496151",
    "ad_library_url": "=https://www.facebook.com/ads/library/?id=1584027789529393"
  },
  {
    "ad_id": "1369862538228467",
    "brand": "PUMA",
    "title": "=PUMA Tackle Heritage low-top sneaker combines retro design with modern street style.",
    "offer": "=PUMA Tackle Heritage 低筒運動鞋融合復古設計與現代街頭風格。",
    "lang": "bilingual",
    "score": "=5",
    "logo": "=https://scontent-fco2-1.xx.fbcdn.net/v/t39.35426-6/648670346_955098603529022_5827879654975112665_n.jpg?stp=dst-jpg_s60x60_tt6&_nc_cat=103&ccb=1-7&_nc_sid=c53f8f&_nc_ohc=m1nQ7ZZphrAQ7kNvwE3uAVs&_nc_oc=Adnr77cNaikIlXe9nmD1q826Lex0vgm_7aMxNlyfCJ1UZLC2y86v1h8nJOv3TWRT_DA&_nc_zt=14&_nc_ht=scontent-fco2-1.xx&_nc_gid=OZ3G3lHuRwmK7U8NyCsoHg&_nc_ss=8&oh=00_Afw5yP9Qop8UqdUZY9ilfVZGgf29fMYMg6AlKWmarWd-Vg&oe=69BEC43F",
    "image_url": "=https://scontent-fco2-1.xx.fbcdn.net/v/t39.35426-6/648489471_2412759242511623_3490523457357472945_n.jpg?stp=dst-jpg_s600x600_tt6&_nc_cat=106&ccb=1-7&_nc_sid=c53f8f&_nc_ohc=FJj1-ssUtV4Q7kNvwHx1p3Z&_nc_oc=AdneYO_4r93HVDvClIizX9JknBPdX-UcPxJ0vd8Dr57kY5gdx49Y7d2qUHW-nKx5FBQ&_nc_zt=14&_nc_ht=scontent-fco2-1.xx&_nc_gid=OZ3G3lHuRwmK7U8NyCsoHg&_nc_ss=8&oh=00_AfzaYzHC0x98ZLfk0TbUTPtEYVW5Gi3pHjhDcvY2cCV-vw&oe=69BEE321",
    "video_url": "=",
    "category": "fashion",
    "valid_until": "",
    "scraped_at": "2026-03-17T10:33:20.495784",
    "ad_library_url": "=https://www.facebook.com/ads/library/?id=1369862538228467"
  },
  {
    "ad_id": "1135588788597320",
    "brand": "PUMA",
    "title": "=New seasonal sports and fashion products with free shipping and member exclusive deals.",
    "offer": "=全新季度運動及時尚產品，免運費及會員專屬優惠。",
    "lang": "zh",
    "score": "=6",
    "logo": "=https://scontent-fco2-1.xx.fbcdn.net/v/t39.35426-6/587004083_769217216178991_6058621657611027301_n.jpg?stp=dst-jpg_s60x60_tt6&_nc_cat=103&ccb=1-7&_nc_sid=c53f8f&_nc_ohc=PaziEAMSkNsQ7kNvwE72W8P&_nc_oc=AdkNfFYOOvJ2W9jW1ddkWIAIR25Ee71vnIJ1HVYAkpf6TcVQduG9y9z890U0vcInnPg&_nc_zt=14&_nc_ht=scontent-fco2-1.xx&_nc_gid=OZ3G3lHuRwmK7U8NyCsoHg&_nc_ss=8&oh=00_Afx6nBPf-EYFekOGusF_7TIJW2TnLC_uN3d08EEjU8VP9Q&oe=69BEDED2",
    "image_url": "=https://scontent-fco2-1.xx.fbcdn.net/v/t39.35426-6/584907489_32879914754940271_2603252650710598248_n.jpg?stp=dst-jpg_s600x600_tt6&_nc_cat=101&ccb=1-7&_nc_sid=c53f8f&_nc_ohc=dcmRTkSQdxAQ7kNvwHQn1p8&_nc_oc=AdnDvw6g47MPmEwc73Fbmcb3QSS-nwL6QX_pYQdZbdHnNouTobcp4IsHYN8gSaOU_8Q&_nc_zt=14&_nc_ht=scontent-fco2-1.xx&_nc_gid=OZ3G3lHuRwmK7U8NyCsoHg&_nc_ss=8&oh=00_AfwbV2-OAYn3Eax7hWnGbyZKF4FM_XWVBSq-WyVIscB96w&oe=69BECA25",
    "video_url": "=",
    "category": "fashion",
    "valid_until": "",
    "scraped_at": "2026-03-17T10:33:20.495586",
    "ad_library_url": "=https://www.facebook.com/ads/library/?id=1135588788597320"
  },
  {
    "ad_id": "784103714748748",
    "brand": "PUMA",
    "title": "=New seasonal sports and fashion products with free shipping and 7-day returns.",
    "offer": "=全新季度運動及時尚產品，免運費及7日無條件退貨保證。",
    "lang": "zh",
    "score": "=6",
    "logo": "=https://scontent-fco2-1.xx.fbcdn.net/v/t39.35426-6/615568982_2142838889453733_8796318299985911404_n.jpg?stp=dst-jpg_s60x60_tt6&_nc_cat=103&ccb=1-7&_nc_sid=c53f8f&_nc_ohc=hEmnpt22XyYQ7kNvwFIeLDM&_nc_oc=AdkKq8zyxpb31YHglSuM3G3v3DJZAcm2ZSuCTnbc8MYssRacgcSGTt1kq7uvlDxr4Fo&_nc_zt=14&_nc_ht=scontent-fco2-1.xx&_nc_gid=OZ3G3lHuRwmK7U8NyCsoHg&_nc_ss=8&oh=00_AfwQu6NYy-4JAlqWV6D90pCiErcWDYbJX3MhkFcRlR5n8w&oe=69BEDC3E",
    "image_url": "=https://scontent-fco2-1.xx.fbcdn.net/v/t39.35426-6/615395073_2127605951316288_1498199143885478753_n.jpg?stp=dst-jpg_s600x600_tt6&_nc_cat=105&ccb=1-7&_nc_sid=c53f8f&_nc_ohc=k_UIrSTPN54Q7kNvwGLX6hh&_nc_oc=Adlznzvc1imfNx1iaLV6_z5iUBMnCdcYJFuBs3CuEPQaaXojYeAQ3KnCk413hy1e5Dk&_nc_zt=14&_nc_ht=scontent-fco2-1.xx&_nc_gid=OZ3G3lHuRwmK7U8NyCsoHg&_nc_ss=8&oh=00_AfyIK45m-jCgvdDvGPrG3AxX_RJIUcvwnnfsrivzQfzVvQ&oe=69BEFAA7",
    "video_url": "=",
    "category": "fashion",
    "valid_until": "",
    "scraped_at": "2026-03-17T10:33:20.495380",
    "ad_library_url": "=https://www.facebook.com/ads/library/?id=784103714748748"
  },
  {
    "ad_id": "1835457187157757",
    "brand": "PUMA",
    "title": "=New seasonal PUMA sports and fashion products with free shipping and exclusive member benefits.",
    "offer": "=全新季度PUMA運動及時尚產品，免運費及會員專屬優惠。",
    "lang": "zh",
    "score": "=6",
    "logo": "=https://scontent-fco2-1.xx.fbcdn.net/v/t39.35426-6/584268064_725745109957582_541740302844639347_n.jpg?stp=dst-jpg_s60x60_tt6&_nc_cat=111&ccb=1-7&_nc_sid=c53f8f&_nc_ohc=NShY9MPdYw4Q7kNvwEDzuw0&_nc_oc=Adkvf6xU8KkCp6ZL_nmaz3sWbidqpqfkYQ3ObpngUYu7Z1nS7Q41lEsXg9P8CDV14tw&_nc_zt=14&_nc_ht=scontent-fco2-1.xx&_nc_gid=OZ3G3lHuRwmK7U8NyCsoHg&_nc_ss=8&oh=00_AfwZMBXibLWsYdRa67iyUVUE1Otk4nUnxXspcoT6Z2a_aA&oe=69BED71C",
    "image_url": "=https://scontent-fco2-1.xx.fbcdn.net/v/t39.35426-6/583339210_1375642130764381_7028667632923947798_n.jpg?stp=dst-jpg_s600x600_tt6&_nc_cat=100&ccb=1-7&_nc_sid=c53f8f&_nc_ohc=bw0VtnM2g4IQ7kNvwHroK9r&_nc_oc=AdkHROiOcEoyi1dAy1EmHqhwTG_kdp3j_gq0qEbsAEx5n8-yVA3_3H1O4Kn3T8WtaTk&_nc_zt=14&_nc_ht=scontent-fco2-1.xx&_nc_gid=OZ3G3lHuRwmK7U8NyCsoHg&_nc_ss=8&oh=00_Afw58jmv8ioX4eCTsM5WvieFl0i6qyvfvexYZJtsRoWi6g&oe=69BEDE92",
    "video_url": "=",
    "category": "fashion",
    "valid_until": "",
    "scraped_at": "2026-03-17T10:33:20.494908",
    "ad_library_url": "=https://www.facebook.com/ads/library/?id=1835457187157757"
  },
  {
    "ad_id": "1451147613212091",
    "brand": "",
    "title": "Buy one get one free on autumn-winter jackets and hoodies plus discounts.",
    "offer": "秋冬外套及衛衣買一送一，加上折扣優惠。",
    "lang": "zh",
    "score": "10",
    "logo": "https://scontent.fbud7-4.fna.fbcdn.net/v/t39.35426-6/651282396_3966619756964937_9221616903400039211_n.jpg?stp=dst-jpg_s60x60_tt6&_nc_cat=104&ccb=1-7&_nc_sid=c53f8f&_nc_ohc=zuq7n2AO4dkQ7kNvwGoWk5x&_nc_oc=AdmMoC1AHYuD4yRMis6IcVsI7FLw2VOkEHNoxbC-qDXCBJsPs0FGCtto3UpFyfSgOdZL7TygAcamP9QHyKdXROSM&_nc_zt=14&_nc_ht=scontent.fbud7-4.fna&_nc_gid=sKjGrKFzaZaKEdHVqt2pXg&_nc_ss=8&oh=00_AfxS-k9Dv2NIQNNyW9WA1BczI9Xab9Mrc4aYuYqmzMtnsw&oe=69BD8E7C",
    "valid_until": ""
  },
  {
    "ad_id": "1814478032543536",
    "brand": "",
    "title": "Buy one jacket or hoodie, get one free at full price.",
    "offer": "購買外套或衛衣一件，即可免費獲得另一件。",
    "lang": "zh",
    "score": "9",
    "logo": "https://scontent.fbud7-4.fna.fbcdn.net/v/t39.35426-6/648206897_753662360949029_4798018612553958578_n.jpg?stp=dst-jpg_s60x60_tt6&_nc_cat=108&ccb=1-7&_nc_sid=c53f8f&_nc_ohc=1iCFT2Lj_8oQ7kNvwF3oin-&_nc_oc=Admx9x3VJNAu1ulQ3g-ra1t6bsFVBdI2oLldfenw2eibZpF4rh44ih0OOIYSdUzDhLMRVdp1FcOV2GJVgqXdccSq&_nc_zt=14&_nc_ht=scontent.fbud7-4.fna&_nc_gid=sKjGrKFzaZaKEdHVqt2pXg&_nc_ss=8&oh=00_AfwtqZdKDd8NnAUisQNS89LB9ildD7C2NLa-mTe9utXYkQ&oe=69BDA916",
    "valid_until": "2024-03-22"
  },
  {
    "ad_id": "1271309868271277",
    "brand": "",
    "title": "",
    "offer": "",
    "lang": "zh",
    "score": "10",
    "logo": "https://scontent.frke1-1.fna.fbcdn.net/v/t39.35426-6/651161200_1551368105964998_2528640832992164850_n.jpg?stp=dst-jpg_s60x60_tt6&_nc_cat=111&ccb=1-7&_nc_sid=c53f8f&_nc_ohc=yTE70p9knJgQ7kNvwHmCI6V&_nc_oc=AdkQfTc7JQpQcnIyNV9iMj0FxFluMY77gmQAQbIjndh00cPoXsxYmrjDtpaHQOKJqfs&_nc_zt=14&_nc_ht=scontent.frke1-1.fna&_nc_gid=v9fqlzOmFNusODmI7py0wA&_nc_ss=8&oh=00_AfwMAw5VCJPr9RwXH_M2n5UB1M8rwI0mNCM_KWna3c-IWw&oe=69BD7569",
    "valid_until": ""
  },
  {
    "ad_id": "3495340937281868",
    "brand": "",
    "title": "Free personal assistant service for 1O1O and 1O1O HOME customers.",
    "offer": "1O1O及1O1O HOME客戶可免費享用1O1O私人助理服務。",
    "lang": "bilingual",
    "score": "9",
    "logo": "https://scontent.frke1-1.fna.fbcdn.net/v/t39.35426-6/652834029_2402825833489112_654516521085456077_n.jpg?stp=dst-jpg_s60x60_tt6&_nc_cat=109&ccb=1-7&_nc_sid=c53f8f&_nc_ohc=nmnmPmFJLGMQ7kNvwGsLzmg&_nc_oc=AdlPbnh98C8AQddpiaA_9299Wg6nSw54mhGzPQ_swd1YXoiIY6gKJS5d4Fx6KLr0YuE&_nc_zt=14&_nc_ht=scontent.frke1-1.fna&_nc_gid=v9fqlzOmFNusODmI7py0wA&_nc_ss=8&oh=00_Afwd3Oq_KGuSZAUqlWADk8c0yDPDfxr20D39IYzYrq8VhA&oe=69BD9FD8",
    "valid_until": ""
  },
  {
    "ad_id": "1298205759025531",
    "brand": "",
    "title": "Free one-year Perplexity Pro subscription worth HKD 1,488 for selected 1O1O customers.",
    "offer": "精選1O1O客戶可免費享用價值HK$1,488的Perplexity Pro進階AI服務一年。",
    "lang": "zh",
    "score": "10",
    "logo": "https://scontent.frke1-1.fna.fbcdn.net/v/t39.35426-6/651781764_2297308204088701_3492518782142987247_n.jpg?stp=dst-jpg_s60x60_tt6&_nc_cat=110&ccb=1-7&_nc_sid=c53f8f&_nc_ohc=8SLu5iZ5XFQQ7kNvwGja0U7&_nc_oc=Adm17Fah7y-gIDWgXxPoDHuDp7ds8jpk1GLmKlQqto8txoUTfVy1Stun__WqRcwOjWM&_nc_zt=14&_nc_ht=scontent.frke1-1.fna&_nc_gid=v9fqlzOmFNusODmI7py0wA&_nc_ss=8&oh=00_AfxOIjeWtr5SzKmfeRlhfwnM3x_nUDJRdD39sw5baANKQA&oe=69BD8E5C",
    "valid_until": ""
  },
  {
    "ad_id": "1683602532786619",
    "brand": "",
    "title": "",
    "offer": "",
    "lang": "bilingual",
    "score": "10",
    "logo": "https://scontent.frke1-1.fna.fbcdn.net/v/t39.35426-6/651894499_3000015146872471_8384123086205570276_n.jpg?stp=dst-jpg_s60x60_tt6&_nc_cat=110&ccb=1-7&_nc_sid=c53f8f&_nc_ohc=rORdfg5UUc4Q7kNvwGO8oOs&_nc_oc=AdkcnBgabvAlW_mmxtFJE8oBg9zM_dWxyA1-w_lXNHAUGDHM6SQWsTRCZnScES1cVQw&_nc_zt=14&_nc_ht=scontent.frke1-1.fna&_nc_gid=v9fqlzOmFNusODmI7py0wA&_nc_ss=8&oh=00_AfzyaG-e_hvB9zHrt11cs-iK8zORG1r0rnpm0_QtEjL1WQ&oe=69BD774B",
    "valid_until": ""
  },
  {
    "ad_id": "2087696888688702",
    "brand": "",
    "title": "",
    "offer": "",
    "lang": "zh",
    "score": "7",
    "logo": "https://scontent.fbkk14-1.fna.fbcdn.net/v/t39.35426-6/651651635_1894749581406805_3903798565706248715_n.jpg?stp=dst-jpg_s60x60_tt6&_nc_cat=104&ccb=1-7&_nc_sid=c53f8f&_nc_ohc=t4m5w_CibT8Q7kNvwF28std&_nc_oc=Adkfnxd6FlRdioCdM8RnKj-Ilw5IDaKxX3TvrUu882YReyZKuVa829jgIgHUkwAt0S4&_nc_zt=14&_nc_ht=scontent.fbkk14-1.fna&_nc_gid=NQjbihcS0lrE7HoqhRckxw&_nc_ss=8&oh=00_AfyrxXl21YMlcEUSmWfSzVV6QAuD2LEqHI9MecF_gUnE8A&oe=69BD90B4",
    "valid_until": ""
  },
  {
    "ad_id": "1553667829034898",
    "brand": "",
    "title": "",
    "offer": "",
    "lang": "bilingual",
    "score": "10",
    "logo": "https://scontent.frke1-1.fna.fbcdn.net/v/t39.35426-6/651164289_950762381041452_6831660566194127470_n.jpg?stp=dst-jpg_s60x60_tt6&_nc_cat=100&ccb=1-7&_nc_sid=c53f8f&_nc_ohc=AO8pVjim99YQ7kNvwGI9bnt&_nc_oc=Adm33vkteR8-inBxBEovdWU4OsMZg7T_W4nZG65EDEE8b7wedqczUVE6caWL_KcIGnA&_nc_zt=14&_nc_ht=scontent.frke1-1.fna&_nc_gid=v9fqlzOmFNusODmI7py0wA&_nc_ss=8&oh=00_Afw3Vk_wL9U6IQITy6zY04pw0f9sN_QtYs9UVLPgDoiXNg&oe=69BD7F1E",
    "valid_until": ""
  },
  {
    "ad_id": "921856033930213",
    "brand": "",
    "title": "Purchase Samsung Galaxy S26 Ultra and receive free storage upgrade, Perplexity Pro, AI support, and accessories.",
    "offer": "購買Samsung Galaxy S26 Ultra即享免費容量升級、Perplexity Pro、AI支援及配件禮遇。",
    "lang": "bilingual",
    "score": "10",
    "logo": "https://scontent.frke1-1.fna.fbcdn.net/v/t39.35426-6/649857363_943443874802475_1356875333526475311_n.jpg?stp=dst-jpg_s60x60_tt6&_nc_cat=106&ccb=1-7&_nc_sid=c53f8f&_nc_ohc=lvlapvtK0dEQ7kNvwEvTQeN&_nc_oc=Adk1LQOZ3WBh0LVv7jelzjDu7xxXBrU65wmJALrr3DFIhXhSaR81BcTkf1o6QjvTZ-c&_nc_zt=14&_nc_ht=scontent.frke1-1.fna&_nc_gid=v9fqlzOmFNusODmI7py0wA&_nc_ss=8&oh=00_AfxJhs7LDdCManjswCQtCoCgjKyRAc0z1mwTQDKTvKjF8Q&oe=69BD977C",
    "valid_until": "2026-03-31"
  },
  {
    "ad_id": "2087796088431501",
    "brand": "",
    "title": "Purchase Samsung Galaxy S26 Ultra and receive free storage upgrade, Perplexity Pro, AI support, and accessories.",
    "offer": "購買 Samsung Galaxy S26 Ultra 可獲免費容量升級、Perplexity Pro、AI支援及配件。",
    "lang": "bilingual",
    "score": "10",
    "logo": "https://scontent.frke1-1.fna.fbcdn.net/v/t39.35426-6/650894617_1583185376293595_6564623647957833784_n.jpg?stp=dst-jpg_s60x60_tt6&_nc_cat=108&ccb=1-7&_nc_sid=c53f8f&_nc_ohc=yoiAh1qcJTgQ7kNvwEjPNm5&_nc_oc=AdkEmzzn6QXnPn0xxdJpF6MnqLnJh0mfz9IHnEjXhaaPZHenmEsoM8CY426uEW_7diQ&_nc_zt=14&_nc_ht=scontent.frke1-1.fna&_nc_gid=v9fqlzOmFNusODmI7py0wA&_nc_ss=8&oh=00_Afyin2Y8tSGer_8LJfccHMWAIus0e8XEd9ym7XDSRELSVw&oe=69BD74CD",
    "valid_until": "2026-03-31"
  },
  {
    "ad_id": "1447342303660060",
    "brand": "",
    "title": "",
    "offer": "",
    "lang": "zh",
    "score": "7",
    "logo": "https://scontent-zrh1-1.xx.fbcdn.net/v/t39.35426-6/597928200_890364270222100_7181129776298081396_n.jpg?stp=dst-jpg_s60x60_tt6&_nc_cat=106&ccb=1-7&_nc_sid=c53f8f&_nc_ohc=dChTwwvrmwIQ7kNvwE4QwBL&_nc_oc=AdkcKVC-f7Yg5Retk-yZfMM_4caSr2q36NE2qG_v2N5rlWxTuvMNIa8CQ8sJ7GOT760&_nc_zt=14&_nc_ht=scontent-zrh1-1.xx&_nc_gid=IwhrfhPKH72-2dJjkOf9zA&_nc_ss=8&oh=00_Afw2wevUyHwiFBpYOm0JkvBKuICgqxqu5n4aw2__OxFcIw&oe=69BD892F",
    "valid_until": ""
  },
  {
    "ad_id": "3835023579967272",
    "brand": "",
    "title": "Samsung Galaxy S26 Ultra with free storage upgrade, AI services, accessories and multiple gift bundles.",
    "offer": "購買Samsung Galaxy S26 Ultra即享免費容量升級、AI服務、配件及多重禮遇套裝。",
    "lang": "zh",
    "score": "10",
    "logo": "https://scontent.frke1-1.fna.fbcdn.net/v/t39.35426-6/652894143_1594293875553774_167761522423457482_n.jpg?stp=dst-jpg_s60x60_tt6&_nc_cat=107&ccb=1-7&_nc_sid=c53f8f&_nc_ohc=-QP-PhI7v9gQ7kNvwHYz_w4&_nc_oc=AdnMka17xvFOGT2HYp-CCHqBmvKqizEIBe3mfdXxj6BiTWvgdpHzdPdAm1NZIeU3y-Y&_nc_zt=14&_nc_ht=scontent.frke1-1.fna&_nc_gid=v9fqlzOmFNusODmI7py0wA&_nc_ss=8&oh=00_Afy5Ezz8cha7yYt8nh30dHvVWW4d0nku3Psex_HBjmIFjw&oe=69BD7A2A",
    "valid_until": "2026-03-31"
  },
  {
    "ad_id": "2475196409562843",
    "brand": "",
    "title": "5G data roaming package with free 30-day travel insurance for Asia-Pacific destinations.",
    "offer": "5G黃金漫遊數據流量組合送免費30日旅遊保險。",
    "lang": "bilingual",
    "score": "10",
    "logo": "https://scontent.frke1-1.fna.fbcdn.net/v/t39.35426-6/651164289_950762381041452_6831660566194127470_n.jpg?stp=dst-jpg_s60x60_tt6&_nc_cat=100&ccb=1-7&_nc_sid=c53f8f&_nc_ohc=AO8pVjim99YQ7kNvwGI9bnt&_nc_oc=Adm33vkteR8-inBxBEovdWU4OsMZg7T_W4nZG65EDEE8b7wedqczUVE6caWL_KcIGnA&_nc_zt=14&_nc_ht=scontent.frke1-1.fna&_nc_gid=v9fqlzOmFNusODmI7py0wA&_nc_ss=8&oh=00_Afw3Vk_wL9U6IQITy6zY04pw0f9sN_QtYs9UVLPgDoiXNg&oe=69BD7F1E",
    "valid_until": ""
  },
  {
    "ad_id": "1425870499007166",
    "brand": "",
    "title": "Samsung Galaxy S26 Ultra with free storage upgrade, AI services, and multiple gifts.",
    "offer": "購買Samsung Galaxy S26 Ultra 享免費容量升級、AI服務及多項禮品。",
    "lang": "zh",
    "score": "10",
    "logo": "https://scontent.frke1-1.fna.fbcdn.net/v/t39.35426-6/652223648_1080408525148748_4519058351041334888_n.jpg?stp=dst-jpg_s60x60_tt6&_nc_cat=102&ccb=1-7&_nc_sid=c53f8f&_nc_ohc=jbQvJl7i-2YQ7kNvwHDuNqX&_nc_oc=AdnvlNEbQJQ2Q9AR9wfw6jKtm3O7nvsY46Csq9CiQ8mDcpOgXaAGeNMjHCqTrSinoXY&_nc_zt=14&_nc_ht=scontent.frke1-1.fna&_nc_gid=v9fqlzOmFNusODmI7py0wA&_nc_ss=8&oh=00_AfwMUGr7llVFOxOxo5ZKcuvFjTcUMXDk6jY2dIGogu_TQw&oe=69BDA8A7",
    "valid_until": "2026-03-31"
  },
  {
    "ad_id": "931234509603738",
    "brand": "",
    "title": "Purchase Samsung Galaxy S26 Ultra with free storage upgrade, AI services, and multiple gifts.",
    "offer": "購買Samsung Galaxy S26 Ultra享免費儲存空間升級、AI服務及多項禮品。",
    "lang": "bilingual",
    "score": "10",
    "logo": "https://scontent.frke1-1.fna.fbcdn.net/v/t39.35426-6/649487404_2504606159974367_2224316406515740655_n.jpg?stp=dst-jpg_s60x60_tt6&_nc_cat=108&ccb=1-7&_nc_sid=c53f8f&_nc_ohc=zEEfkq7Y9LwQ7kNvwFKIr41&_nc_oc=Adn0qZECVaHnM1w48TTOT2NdjXVI_wxaaTQgXBfeZbc9mx_ASBfoI_xvXFuggOol5FA&_nc_zt=14&_nc_ht=scontent.frke1-1.fna&_nc_gid=v9fqlzOmFNusODmI7py0wA&_nc_ss=8&oh=00_Afz4cZlSF6NoSk5cM9UwxyTA9BwVNYvBMQ2dJMMJpNjShw&oe=69BD74A5",
    "valid_until": "2026-03-31"
  },
  {
    "ad_id": "2860082741050611",
    "brand": "",
    "title": "Purchase Samsung Galaxy S26 Ultra and receive free storage upgrade, AI services, and multiple gifts.",
    "offer": "購買三星Galaxy S26 Ultra，免費升級儲存空間、AI服務及多項禮品。",
    "lang": "bilingual",
    "score": "10",
    "logo": "https://scontent.frke1-1.fna.fbcdn.net/v/t39.35426-6/651412521_1407516351123634_4360399981243832520_n.jpg?stp=dst-jpg_s60x60_tt6&_nc_cat=108&ccb=1-7&_nc_sid=c53f8f&_nc_ohc=xcjbeNlkM7IQ7kNvwFNqphm&_nc_oc=AdkXKpatl5sOnPoPnE76kt0PllI1ymfD7dLOil2uDMdWoPYtM7Ri9jN5FujwBi5m5O4&_nc_zt=14&_nc_ht=scontent.frke1-1.fna&_nc_gid=v9fqlzOmFNusODmI7py0wA&_nc_ss=8&oh=00_Afye3DCDn740W-SDWcnif-xoLgMc12tFYVLQ6SDpqh0i0w&oe=69BDA9DC",
    "valid_until": "2026-03-31"
  },
  {
    "ad_id": "3635232013283620",
    "brand": "",
    "title": "Buy Rokid AI Glasses Style, get HKD 200 discount plus free charging capsule worth HKD 799.",
    "offer": "購買Rokid AI眼鏡享HKD 200折扣及價值HKD 799充電膠囊免費贈送。",
    "lang": "bilingual",
    "score": "10",
    "logo": "https://scontent.frke1-1.fna.fbcdn.net/v/t39.35426-6/651894499_3000015146872471_8384123086205570276_n.jpg?stp=dst-jpg_s60x60_tt6&_nc_cat=110&ccb=1-7&_nc_sid=c53f8f&_nc_ohc=rORdfg5UUc4Q7kNvwGO8oOs&_nc_oc=AdkcnBgabvAlW_mmxtFJE8oBg9zM_dWxyA1-w_lXNHAUGDHM6SQWsTRCZnScES1cVQw&_nc_zt=14&_nc_ht=scontent.frke1-1.fna&_nc_gid=v9fqlzOmFNusODmI7py0wA&_nc_ss=8&oh=00_AfzyaG-e_hvB9zHrt11cs-iK8zORG1r0rnpm0_QtEjL1WQ&oe=69BD774B",
    "valid_until": ""
  },
  {
    "ad_id": "901880572676104",
    "brand": "",
    "title": "5G data roaming pass with free 30-day travel insurance for Asia-Pacific destinations.",
    "offer": "5G黃金漫遊數據流量組合，附贈30日免費旅遊保險。",
    "lang": "bilingual",
    "score": "10",
    "logo": "https://scontent.frke1-1.fna.fbcdn.net/v/t39.35426-6/652324648_1246069580924260_5468728472618598600_n.jpg?stp=dst-jpg_s60x60_tt6&_nc_cat=105&ccb=1-7&_nc_sid=c53f8f&_nc_ohc=8xRW4Pc9WQQQ7kNvwHRa4DT&_nc_oc=AdnNSiRSk6w2TCDHCKVprjUxUSvLzFXXECMzdqVLCqp35cb-1f1Qrc1mAC9RaxZgj-8&_nc_zt=14&_nc_ht=scontent.frke1-1.fna&_nc_gid=v9fqlzOmFNusODmI7py0wA&_nc_ss=8&oh=00_AfwAsGDce_SP8PcbREf3FUl28j77ZNGZ9LfgcMHnX6Jmig&oe=69BD78F2",
    "valid_until": ""
  },
  {
    "ad_id": "1474885944354699",
    "brand": "",
    "title": "Free Personal Assistant service for 1O1O and 1O1O HOME customers.",
    "offer": "1O1O 及 1O1O HOME 客戶可免費享用 1O1O 私人助理服務。",
    "lang": "bilingual",
    "score": "9",
    "logo": "https://scontent.frke1-1.fna.fbcdn.net/v/t39.35426-6/652834029_2402825833489112_654516521085456077_n.jpg?stp=dst-jpg_s60x60_tt6&_nc_cat=109&ccb=1-7&_nc_sid=c53f8f&_nc_ohc=nmnmPmFJLGMQ7kNvwGsLzmg&_nc_oc=AdlPbnh98C8AQddpiaA_9299Wg6nSw54mhGzPQ_swd1YXoiIY6gKJS5d4Fx6KLr0YuE&_nc_zt=14&_nc_ht=scontent.frke1-1.fna&_nc_gid=v9fqlzOmFNusODmI7py0wA&_nc_ss=8&oh=00_Afwd3Oq_KGuSZAUqlWADk8c0yDPDfxr20D39IYzYrq8VhA&oe=69BD9FD8",
    "valid_until": ""
  },
  {
    "ad_id": "774639892369793",
    "brand": "",
    "title": "Buy one jacket or sweater, get one free until March 22.",
    "offer": "外套及衛衣買一送一，優惠期至3月22日。",
    "lang": "zh",
    "score": "9",
    "logo": "https://scontent.fbud7-3.fna.fbcdn.net/v/t39.35426-6/648293574_1984517339077722_2268796285984353679_n.jpg?stp=dst-jpg_s60x60_tt6&_nc_cat=105&ccb=1-7&_nc_sid=c53f8f&_nc_ohc=dTpFdkGJpdgQ7kNvwF_RHtZ&_nc_oc=AdmiI1zvl9ss7ikf4g6aw-eHc4n0mPgfZzk2B5X1O8cJjbInKVSbHqdK5iZLlVLc6uZ-xt3TfnVWw_uXZm33ERKP&_nc_zt=14&_nc_ht=scontent.fbud7-3.fna&_nc_gid=sKjGrKFzaZaKEdHVqt2pXg&_nc_ss=8&oh=00_AfxQGmaSxjfVbUKWQnxz1TXO8qYhXUxNalju18AQEgojnA&oe=69BD88F0",
    "valid_until": "2024-03-22"
  },
  {
    "ad_id": "1558785836252570",
    "brand": "",
    "title": "Free one-year Perplexity Pro subscription worth HKD 1,488 for selected 1O1O customers.",
    "offer": "精選1O1O客戶可免費享用價值HK$1,488的Perplexity Pro進階AI服務一年。",
    "lang": "zh",
    "score": "10",
    "logo": "https://scontent.frke1-1.fna.fbcdn.net/v/t39.35426-6/651161200_1551368105964998_2528640832992164850_n.jpg?stp=dst-jpg_s60x60_tt6&_nc_cat=111&ccb=1-7&_nc_sid=c53f8f&_nc_ohc=yTE70p9knJgQ7kNvwHmCI6V&_nc_oc=AdkQfTc7JQpQcnIyNV9iMj0FxFluMY77gmQAQbIjndh00cPoXsxYmrjDtpaHQOKJqfs&_nc_zt=14&_nc_ht=scontent.frke1-1.fna&_nc_gid=v9fqlzOmFNusODmI7py0wA&_nc_ss=8&oh=00_AfwMAw5VCJPr9RwXH_M2n5UB1M8rwI0mNCM_KWna3c-IWw&oe=69BD7569",
    "valid_until": ""
  },
  {
    "ad_id": "998268472533337",
    "brand": "",
    "title": "Samsung Galaxy S26 from $0 with world data plan, free VPN, and accessories.",
    "offer": "Samsung Galaxy S26低至$0出機，包世界數據及免費VPN與配件。",
    "lang": "zh",
    "score": "9",
    "logo": "https://scontent.fdac41-1.fna.fbcdn.net/v/t39.35426-6/649081212_1210594560841566_3293983375023248859_n.jpg?stp=dst-jpg_s60x60_tt6&_nc_cat=100&ccb=1-7&_nc_sid=c53f8f&_nc_ohc=efs6-DqDgwoQ7kNvwEUJW-Z&_nc_oc=AdnigCurX7yu2erflENRsJXoPS9R9HmnL0Rumqrd9N9QiGgMdArGQBsvcdkMm9gqxFY&_nc_zt=14&_nc_ht=scontent.fdac41-1.fna&_nc_gid=qD4nznM_nfHDZoO8OTRpqw&_nc_ss=8&oh=00_AfwqB4qf2L8klWOOCnqE30ULAYPaQy5jKlXh_Ewk7R0Wog&oe=69BD973F",
    "valid_until": "2025-03-31"
  }
]